2° semestre/arquitetura01/Guia_09/Guia_0905.v
// ---------------------------
// -- test clock generator (6)
// -- Rayssa Mell de Souza Silva - 860210
// ---------------------------

module clock ( output clk );
 reg    clk;
 initial
  begin
    clk = 1'b0;
 end

 always
  begin
    #12 clk = ~clk;
  end
endmodule

module pulse ( signal, clock );
  input clock;
  output signal;
  reg signal;

  always @ ( posedge clock )
    begin
    signal = 1'b1;
    #4 signal = 1'b0;
    #4 signal = 1'b1;
    end
endmodule // pulse

module Guia_0905;
    wire clock;
    reg p;
    wire p1;
    
    //instancia
    clock clk ( clock );
    pulse pulse1 ( p1, clock );
   
    initial begin
        p = 1'b0;
    end
    initial begin
    $dumpfile ( "Guia_0905.vcd" );
    $dumpvars ( 1, clock, p1, p);
    #060 p = 1'b1;
    #120 p = 1'b0;
    #180 p = 1'b1;
    #240 p = 1'b0;
    #300 p = 1'b1;
    #360 p = 1'b0;
    #376 $finish;
    end
endmodule // Guia_0905

2° semestre/arquitetura01/Guia_09/Guia_0905.vcd
$date
	Sat Sep 28 10:24:52 2024
$end
$version
	Icarus Verilog
$end
$timescale
	1s
$end
$scope module Guia_0905 $end
$var wire 1 ! clock $end
$upscope $end
$scope module Guia_0905 $end
$var wire 1 " p1 $end
$upscope $end
$scope module Guia_0905 $end
$var reg 1 # p $end
$upscope $end
$enddefinitions $end
$comment Show the parameter values. $end
$dumpall
$end
#0
$dumpvars
0#
x"
0!
$end
#12
1"
1!
#16
0"
#20
1"
#24
0!
#36
1!
#40
0"
#44
1"
#48
0!
#60
1!
1#
#64
0"
#68
1"
#72
0!
#84
1!
#88
0"
#92
1"
#96
0!
#108
1!
#112
0"
#116
1"
#120
0!
#132
1!
#136
0"
#140
1"
#144
0!
#156
1!
#160
0"
#164
1"
#168
0!
#180
1!
0#
#184
0"
#188
1"
#192
0!
#204
1!
#208
0"
#212
1"
#216
0!
#228
1!
#232
0"
#236
1"
#240
0!
#252
1!
#256
0"
#260
1"
#264
0!
#276
1!
#280
0"
#284
1"
#288
0!
#300
1!
#304
0"
#308
1"
#312
0!
#324
1!
#328
0"
#332
1"
#336
0!
#348
1!
#352
0"
#356
1"
#360
0!
1#
#372
1!
#376
0"
#380
1"
#384
0!
#396
1!
#400
0"
#404
1"
#408
0!
#420
1!
#424
0"
#428
1"
#432
0!
#444
1!
#448
0"
#452
1"
#456
0!
#468
1!
#472
0"
#476
1"
#480
0!
#492
1!
#496
0"
#500
1"
#504
0!
#516
1!
#520
0"
#524
1"
#528
0!
#540
1!
#544
0"
#548
1"
#552
0!
#564
1!
#568
0"
#572
1"
#576
0!
#588
1!
#592
0"
#596
1"
#600
0!
0#
#612
1!
#616
0"
#620
1"
#624
0!
#636
1!
#640
0"
#644
1"
#648
0!
#660
1!
#664
0"
#668
1"
#672
0!
#684
1!
#688
0"
#692
1"
#696
0!
#708
1!
#712
0"
#716
1"
#720
0!
#732
1!
#736
0"
#740
1"
#744
0!
#756
1!
#760
0"
#764
1"
#768
0!
#780
1!
#784
0"
#788
1"
#792
0!
#804
1!
#808
0"
#812
1"
#816
0!
#828
1!
#832
0"
#836
1"
#840
0!
#852
1!
#856
0"
#860
1"
#864
0!
#876
1!
#880
0"
#884
1"
#888
0!
#900
1!
1#
#904
0"
#908
1"
#912
0!
#924
1!
#928
0"
#932
1"
#936
0!
#948
1!
#952
0"
#956
1"
#960
0!
#972
1!
#976
0"
#980
1"
#984
0!
#996
1!
#1000
0"
#1004
1"
#1008
0!
#1020
1!
#1024
0"
#1028
1"
#1032
0!
#1044
1!
#1048
0"
#1052
1"
#1056
0!
#1068
1!
#1072
0"
#1076
1"
#1080
0!
#1092
1!
#1096
0"
#1100
1"
#1104
0!
#1116
1!
#1120
0"
#1124
1"
#1128
0!
#1140
1!
#1144
0"
#1148
1"
#1152
0!
#1164
1!
#1168
0"
#1172
1"
#1176
0!
#1188
1!
#1192
0"
#1196
1"
#1200
0!
#1212
1!
#1216
0"
#1220
1"
#1224
0!
#1236
1!
#1240
0"
#1244
1"
#1248
0!
#1260
1!
0#
#1264
0"
#1268
1"
#1272
0!
#1284
1!
#1288
0"
#1292
1"
#1296
0!
#1308
1!
#1312
0"
#1316
1"
#1320
0!
#1332
1!
#1336
0"
#1340
1"
#1344
0!
#1356
1!
#1360
0"
#1364
1"
#1368
0!
#1380
1!
#1384
0"
#1388
1"
#1392
0!
#1404
1!
#1408
0"
#1412
1"
#1416
0!
#1428
1!
#1432
0"
#1436
1"
#1440
0!
#1452
1!
#1456
0"
#1460
1"
#1464
0!
#1476
1!
#1480
0"
#1484
1"
#1488
0!
#1500
1!
#1504
0"
#1508
1"
#1512
0!
#1524
1!
#1528
0"
#1532
1"
#1536
0!
#1548
1!
#1552
0"
#1556
1"
#1560
0!
#1572
1!
#1576
0"
#1580
1"
#1584
0!
#1596
1!
#1600
0"
#1604
1"
#1608
0!
#1620
1!
#1624
0"
#1628
1"
